MANIFEST.in
README.md
setup.py
EzCSS/EzCSS.py
EzCSS/__init__.py
EzHTML/EzHTML.py
EzHTML/__init__.py
EzJS/EzJS.py
EzJS/__init__.py
EzWeb_Mad.egg-info/PKG-INFO
EzWeb_Mad.egg-info/SOURCES.txt
EzWeb_Mad.egg-info/dependency_links.txt
EzWeb_Mad.egg-info/requires.txt
EzWeb_Mad.egg-info/top_level.txt