Metadata-Version: 2.1
Name: EzWeb-Mad
Version: 0.1.0
Summary: A module to make more ez to coding ur web
Author: mad6453
Classifier: Programming Language :: Python :: 3
Classifier: License :: OSI Approved :: MIT License
Classifier: Operating System :: OS Independent
Requires-Python: >=3.6
Requires-Dist: Flask
